litefaas_py/.gitignore
litefaas_py/__init__.py
litefaas_py/core.py
litefaas_py/Dockerfile
litefaas_py/requirements.txt
litefaas_py/test/async_server.py
litefaas_py/test/cpu_async_server.py
litefaas_py/test/cpu_process_server.py
litefaas_py/test/cpu_test_client.py
litefaas_py/test/cpu_thread_server.py
litefaas_py/test/example_client_simple.py
litefaas_py/test/test_client.py
litefaas_py/test/thread_server.py
litefaas_py-0.2.0.dist-info/METADATA
litefaas_py-0.2.0.dist-info/WHEEL
litefaas_py-0.2.0.dist-info/RECORD
